rxn/metrics/__init__.py
rxn/metrics/class_tokens.py
rxn/metrics/classification_translation.py
rxn/metrics/context_metrics.py
rxn/metrics/forward_metrics.py
rxn/metrics/metrics.py
rxn/metrics/metrics_calculator.py
rxn/metrics/metrics_files.py
rxn/metrics/py.typed
rxn/metrics/retro_metrics.py
rxn/metrics/run_metrics.py
rxn/metrics/tokenize_file.py
rxn/metrics/true_reactant_accuracy.py
rxn/metrics/utils.py
rxn/metrics/scripts/__init__.py
rxn/metrics/scripts/ensure_data_dimension.py
rxn/metrics/scripts/join_data_files.py
rxn/metrics/scripts/parse_metrics_into_csv.py
rxn/metrics/scripts/prepare_context_metrics.py
rxn/metrics/scripts/prepare_forward_metrics.py
rxn/metrics/scripts/prepare_retro_metrics.py
rxn/metrics/scripts/reorder_retro_predictions_class_token.py
rxn/metrics/scripts/rxn_evaluate_metrics.py
rxn_metrics-1.1.0.dist-info/LICENSE
rxn_metrics-1.1.0.dist-info/METADATA
rxn_metrics-1.1.0.dist-info/WHEEL
rxn_metrics-1.1.0.dist-info/entry_points.txt
rxn_metrics-1.1.0.dist-info/top_level.txt
rxn_metrics-1.1.0.dist-info/RECORD
