Metadata-Version: 2.1
Name: rxn-metrics
Version: 1.1.0
Summary: Metrics for RXN models
Home-page: https://github.com/rxn4chemistry/rxn-metrics
Author: IBM RXN team
License: MIT
Project-URL: Documentation, https://rxn4chemistry.github.io/rxn-metrics/
Project-URL: Repository, https://github.com/rxn4chemistry/rxn-metrics
Classifier: Operating System :: OS Independent
Classifier: Programming Language :: Python :: 3
Classifier: Programming Language :: Python :: 3.6
Classifier: Programming Language :: Python :: 3.7
Classifier: Programming Language :: Python :: 3.8
Requires-Python: >=3.6
License-File: LICENSE
Requires-Dist: click (>=8.0)
Requires-Dist: pandas (>=1.1.0)
Requires-Dist: rxn-chem-utils (>=1.3.0)
Requires-Dist: rxn-onmt-models (>=1.0.0)
Requires-Dist: rxn-onmt-utils (>=1.0.0)
Requires-Dist: rxn-utils (>=1.1.9)
Provides-Extra: dev
Requires-Dist: black (>=22.3.0) ; extra == 'dev'
Requires-Dist: bump2version (>=1.0.1) ; extra == 'dev'
Requires-Dist: flake8 (>=3.8.4) ; extra == 'dev'
Requires-Dist: isort (>=5.10.1) ; extra == 'dev'
Requires-Dist: mypy (>=0.910) ; extra == 'dev'
Requires-Dist: pytest (>=5.3.4) ; extra == 'dev'
Requires-Dist: types-setuptools (>=57.4.14) ; extra == 'dev'
Provides-Extra: rdkit
Requires-Dist: rdkit-pypi (>=2021.3.2) ; (python_version < "3.7") and extra == 'rdkit'
Requires-Dist: rdkit (>=2022.3.4) ; (python_version >= "3.7") and extra == 'rdkit'
Provides-Extra: rxnmapper
Requires-Dist: rxnmapper (>=0.3.0) ; extra == 'rxnmapper'
Requires-Dist: transformers (<4.23.0) ; extra == 'rxnmapper'
